yarf/__init__.py
yarf/version.py
yarf-0.1.0.dist-info/METADATA
yarf-0.1.0.dist-info/WHEEL
yarf-0.1.0.dist-info/RECORD
