Metadata-Version: 2.1
Name: yarf
Version: 0.1.0
Summary: Yet Another Raft Framework
License: MIT
Author: Ivan Sitkin
Author-email: alvinera@yandex.ru
Requires-Python: >=3.10,<3.13
Classifier: License :: OSI Approved :: MIT License
Classifier: Programming Language :: Python :: 3
Classifier: Programming Language :: Python :: 3.10
Classifier: Programming Language :: Python :: 3.11
Classifier: Programming Language :: Python :: 3.12
